packg/__init__.py
packg/__main__.py
packg/caching.py
packg/constclass.py
packg/debugging.py
packg/dtime.py
packg/log.py
packg/magic.py
packg/maths.py
packg/misc.py
packg/packaging.py
packg/paths.py
packg/stats.py
packg/tqdmext.py
packg/typext.py
packg/cli/__init__.py
packg/cli/check_dir_size.py
packg/cli/cleanup_builds.py
packg/cli/count_endings.py
packg/cli/count_lines.py
packg/cli/create_package_autocomplete.py
packg/cli/download_list_of_urls.py
packg/cli/import_all.py
packg/cli/keep_remote_synced.py
packg/cli/multiproc_example.py
packg/cli/pip_update_all.py
packg/cli/print_paths.py
packg/iotools/__init__.py
packg/iotools/compress.py
packg/iotools/encoding.py
packg/iotools/file_indexer.py
packg/iotools/file_reader.py
packg/iotools/folder.py
packg/iotools/git_root_finder.py
packg/iotools/git_status_checker.py
packg/iotools/jsoncacher.py
packg/iotools/jsonext.py
packg/iotools/jsonext_encoder.py
packg/iotools/misc.py
packg/iotools/numpyext.py
packg/iotools/pathspec_matcher.py
packg/iotools/tomlext.py
packg/iotools/tsvext.py
packg/iotools/yamlext.py
packg/multiproc/__init__.py
packg/multiproc/multiproc_fn.py
packg/multiproc/multiproc_producer_consumer.py
packg/multiproc/multiproc_utils.py
packg/multiproc/multiproc_worker.py
packg/strings/__init__.py
packg/strings/abbreviations.py
packg/strings/base64tools.py
packg/strings/formatters.py
packg/strings/hasher.py
packg/strings/quote_urlparse.py
packg/strings/regexext.py
packg/strings/tabul.py
packg/system/__init__.py
packg/system/systemcall.py
packg/system/timeout.py
packg/testing/__init__.py
packg/testing/fixture_webserver.py
packg/testing/import_from_source.py
packg/testing/setup_tests.py
packg/web/__init__.py
packg/web/file_downloader.py
packg/web/robust_request.py
packg/web/socket_disabler.py
packg-0.33.12.dist-info/licenses/LICENSE
packg-0.33.12.dist-info/METADATA
packg-0.33.12.dist-info/WHEEL
packg-0.33.12.dist-info/top_level.txt
packg-0.33.12.dist-info/zip-safe
packg-0.33.12.dist-info/RECORD
