Metadata-Version: 2.4
Name: packg
Version: 0.33.12
Summary: Collection of utilities used in other python projects.
Author: simon-ging
License: Apache-2.0
Project-URL: Project-URL, https://github.com/simon-ging/packg
Keywords: attrs,typing,dict,attr
Platform: any
Classifier: Development Status :: 3 - Alpha
Classifier: Intended Audience :: Developers
Classifier: License :: OSI Approved :: Apache Software License
Classifier: Natural Language :: English
Classifier: Programming Language :: Python :: 3.8
Classifier: Programming Language :: Python :: 3.9
Classifier: Programming Language :: Python :: 3.10
Classifier: Programming Language :: Python :: 3.11
Classifier: Programming Language :: Python :: 3.12
Classifier: Programming Language :: Python :: 3.13
Classifier: Operating System :: OS Independent
Classifier: Topic :: Software Development :: Version Control :: Git
Requires-Python: >=3.8
License-File: LICENSE
Requires-Dist: typedparser
Requires-Dist: attrs
Requires-Dist: numpy
Requires-Dist: joblib
Requires-Dist: loguru
Requires-Dist: natsort
Requires-Dist: pyyaml
Requires-Dist: python-dotenv
Requires-Dist: pathspec
Requires-Dist: zstandard
Requires-Dist: tqdm
Requires-Dist: requests
Requires-Dist: deprecated
Requires-Dist: tomlkit
Requires-Dist: chardet
Requires-Dist: json5
Dynamic: license-file
